./LICENSE
./PKG-INFO
./README.md
./__init__.py
./openapi.json
./pyproject.toml
./server.py
bach_ghibli_image_generator_api_open_ai_4o_image_generation_free-1.0.0.dist-info/METADATA
bach_ghibli_image_generator_api_open_ai_4o_image_generation_free-1.0.0.dist-info/WHEEL
bach_ghibli_image_generator_api_open_ai_4o_image_generation_free-1.0.0.dist-info/entry_points.txt
bach_ghibli_image_generator_api_open_ai_4o_image_generation_free-1.0.0.dist-info/licenses/LICENSE
bach_ghibli_image_generator_api_open_ai_4o_image_generation_free-1.0.0.dist-info/RECORD
