Metadata-Version: 2.4
Name: bach-ghibli_image_generator_api_open_ai_4o_image_generation_free
Version: 1.0.0
Summary: MCP server for accessing Ghibli Image Generator Api Open Ai 4O Image Generation Free API
Project-URL: Homepage, https://github.com/bachstudio/bach-ghibli_image_generator_api_open_ai_4o_image_generation_free
Project-URL: Repository, https://github.com/bachstudio/bach-ghibli_image_generator_api_open_ai_4o_image_generation_free
Project-URL: Documentation, https://github.com/bachstudio/bach-ghibli_image_generator_api_open_ai_4o_image_generation_free#readme
Project-URL: Bug Tracker, https://github.com/bachstudio/bach-ghibli_image_generator_api_open_ai_4o_image_generation_free/issues
Author: bachstudio
License: MIT License
License-File: LICENSE
Keywords: api,ghibli_image_generator_api_open_ai_4o_image_generation_free,mcp,model-context-protocol
Classifier: Development Status :: 4 - Beta
Classifier: Intended Audience :: Developers
Classifier: License :: OSI Approved :: MIT License
Classifier: Programming Language :: Python :: 3
Classifier: Programming Language :: Python :: 3.10
Classifier: Programming Language :: Python :: 3.11
Classifier: Programming Language :: Python :: 3.12
Requires-Python: >=3.10
Requires-Dist: fastmcp>=2.0.0
Requires-Dist: httpx>=0.25.0
Provides-Extra: dev
Requires-Dist: black>=23.0.0; extra == 'dev'
Requires-Dist: pytest>=7.0.0; extra == 'dev'
